eidolon/__init__.py
eidolon/api_request.py
eidolon/tracker.py
eidolon-0.1.4.dist-info/LICENSE.md
eidolon-0.1.4.dist-info/METADATA
eidolon-0.1.4.dist-info/WHEEL
eidolon-0.1.4.dist-info/RECORD
