Metadata-Version: 2.1
Name: eidolon
Version: 0.1.4
Summary: A utility to concurrently make HTTP requests, with an optional rate limit. Powered by asyncio and aiohttp
Home-page: https://github.com/SphericalKat/eidolon
License: MIT
Keywords: asyncio,aiohttp,http,requests,concurrency,rate-limit
Author: Sphericalkat
Author-email: amolele@gmail.com
Requires-Python: >=3.7
Classifier: License :: OSI Approved :: MIT License
Classifier: Programming Language :: Python :: 3
Classifier: Programming Language :: Python :: 3.7
Classifier: Programming Language :: Python :: 3.8
Classifier: Programming Language :: Python :: 3.9
Classifier: Programming Language :: Python :: 3.10
Classifier: Programming Language :: Python :: 3.11
Requires-Dist: aiohttp[speedups] (>=3.8.4,<4.0.0)
Project-URL: Documentation, https://github.com/SphericalKat/eidolon/blob/main/README.md
Project-URL: Repository, https://github.com/SphericalKat/eidolon
